MaoYanFontRecognize/__init__.py
MaoYanFontRecognize/iconfont0.woff
MaoYanFontRecognize/main.py
maoyan_font_recognize-0.1.3.dist-info/LICENSE
maoyan_font_recognize-0.1.3.dist-info/METADATA
maoyan_font_recognize-0.1.3.dist-info/WHEEL
maoyan_font_recognize-0.1.3.dist-info/top_level.txt
maoyan_font_recognize-0.1.3.dist-info/RECORD
