Metadata-Version: 2.1
Name: maoyan-font-recognize
Version: 0.1.3
Summary: A lib to recognize MaoYan font from the offical website.
Home-page: https://github.com/aruiplex/MaoYanFontRecognize
Author: aruix
Author-email: aruix@teaforence.com
License: UNKNOWN
Project-URL: Bug Tracker, https://github.com/aruiplex/MaoYanFontRecognize/issues
Platform: UNKNOWN
Classifier: Programming Language :: Python :: 3
Classifier: License :: OSI Approved :: MIT License
Classifier: Operating System :: OS Independent
Requires-Python: >=3.6
License-File: LICENSE
Requires-Dist: beautifulSoup4
Requires-Dist: fonttools
